Jackknife.cpython-313-x86_64-linux-gnu.so
LinearSystem_1D.cpython-313-x86_64-linux-gnu.so
LinearSystem_2D.cpython-313-x86_64-linux-gnu.so
Tridiag_solve.cpython-313-x86_64-linux-gnu.so
genotype_calculations.cpython-313-x86_64-linux-gnu.so
genotype_calculations_multipop.cpython-313-x86_64-linux-gnu.so
sparse_tallying.cpython-313-x86_64-linux-gnu.so
moments/Demographics1D.py
moments/Demographics2D.py
moments/Demographics3D.py
moments/Godambe.py
moments/Inference.py
moments/Integration.py
moments/Integration_nomig.py
moments/Jackknife.c
moments/Jackknife.pyx
moments/LinearSystem.py
moments/LinearSystem_1D.c
moments/LinearSystem_1D.pyx
moments/LinearSystem_2D.c
moments/LinearSystem_2D.pyx
moments/Manips.py
moments/Misc.py
moments/ModelPlot.py
moments/Numerics.py
moments/Parsing.py
moments/Plotting.py
moments/Reversible.py
moments/Spectrum_mod.py
moments/Tridiag_solve.c
moments/Tridiag_solve.pyx
moments/__init__.py
moments/_version.py
moments/Demes/Demes.py
moments/Demes/DemesUtil.py
moments/Demes/Inference.py
moments/Demes/__init__.py
moments/LD/Demographics1D.py
moments/LD/Demographics2D.py
moments/LD/Demographics3D.py
moments/LD/Godambe.py
moments/LD/Inference.py
moments/LD/LDstats_mod.py
moments/LD/Matrices.py
moments/LD/Numerics.py
moments/LD/Parsing.py
moments/LD/Plotting.py
moments/LD/Util.py
moments/LD/__init__.py
moments/LD/genotype_calculations.c
moments/LD/genotype_calculations.pyx
moments/LD/genotype_calculations_multipop.c
moments/LD/genotype_calculations_multipop.pyx
moments/LD/sparse_tallying.c
moments/LD/sparse_tallying.pyx
moments/LD/stats_from_genotype_counts.py
moments/LD/stats_from_haplotype_counts.py
moments/Triallele/Demographics.py
moments/Triallele/Integration.py
moments/Triallele/Jackknife.py
moments/Triallele/Numerics.py
moments/Triallele/TriSpectrum_mod.py
moments/Triallele/__init__.py
moments/TwoLocus/Demographics.py
moments/TwoLocus/Inference.py
moments/TwoLocus/Integration.py
moments_popgen-1.5.0.dist-info/METADATA
moments_popgen-1.5.0.dist-info/WHEEL
moments_popgen-1.5.0.dist-info/top_level.txt
moments_popgen-1.5.0.dist-info/RECORD
moments_popgen-1.5.0.dist-info/licenses/LICENSE.txt
