Metadata-Version: 2.4
Name: moments-popgen
Version: 1.5.0
Summary: Population genetic statistics for evolutionary inference
Home-page: https://github.com/MomentsLD/moments
Author-email: Aaron Ragsdale <apgragsdale@wisc.edu>, Simon Gravel <simon.gravel@mcgill.ca>
License: MIT
Project-URL: Repository, https://github.com/MomentsLD/moments
Project-URL: Documentation, https://momentsld.github.io/moments/
Requires-Python: <3.14,>=3.10
License-File: LICENSE.txt
Requires-Dist: numpy<3.0,>=2.0
Requires-Dist: cython>=0.25
Requires-Dist: scipy>=1.3
Requires-Dist: mpmath>=1.0
Requires-Dist: demes>=0.2
Dynamic: home-page
Dynamic: license-file
